django_sberbank-0.2.31.dist-info/DESCRIPTION.rst
django_sberbank-0.2.31.dist-info/METADATA
django_sberbank-0.2.31.dist-info/RECORD
django_sberbank-0.2.31.dist-info/SOURCES.txt.py
django_sberbank-0.2.31.dist-info/WHEEL
django_sberbank-0.2.31.dist-info/dependency_links.txt.py
django_sberbank-0.2.31.dist-info/metadata.json
django_sberbank-0.2.31.dist-info/top_level.txt
django_sberbank-0.2.31.dist-info/top_level.txt.py
sberbank/__init__.py
sberbank/admin.py
sberbank/apps.py
sberbank/exceptions.py
sberbank/models.py
sberbank/serializers.py
sberbank/service.py
sberbank/tasks.py
sberbank/urls.py
sberbank/util.py
sberbank/views.py
sberbank/migrations/0001_initial.py
sberbank/migrations/0002_auto_20180802_1820.py
sberbank/migrations/0003_auto_20180804_1932.py
sberbank/migrations/0004_logentry_request_text.py
sberbank/migrations/0005_auto_20180831_0901.py
sberbank/migrations/0006_payment_method.py
sberbank/migrations/__init__.py
