Metadata-Version: 2.0
Name: django-sberbank
Version: 0.2.31
Summary: Django app for Sberbank payments
Home-page: http://github.com/madprogrammer/django-sberbank
Author: Sergey Anufrienko
Author-email: sergey.anoufrienko@gmail.com
License: BSD
Platform: any
Classifier: Programming Language :: Python :: 3
Classifier: License :: OSI Approved :: BSD License
Classifier: Operating System :: OS Independent
Requires-Dist: django
Requires-Dist: djangorestframework
Requires-Dist: jsonfield2
Requires-Dist: requests
